crdata/__init__.py
crdata/conversion/__init__.py
crdata/conversion/factory.py
crdata/conversion/interface.py
crdata/conversion/tabular/__init__.py
crdata/conversion/tabular/factory.py
crdata/conversion/tabular/filters.py
crdata/conversion/tabular/interface.py
crdata/conversion/tabular/job_consumer.py
crdata/conversion/tabular/job_producer.py
crdata/conversion/tabular/planning_problem.py
crdata/conversion/tabular/prototype_scenario.py
crdata/conversion/tabular/windowing.py
crdata/conversion/util/__init__.py
crdata/conversion/util/indicator_inference.py
crdata/conversion/util/planning_problem_utils.py
crdata/conversion/util/runner.py
crdata/conversion/util/trajectory_classification.py
crdata/conversion/util/yaml.py
crdata/datasets/INTERACTION/__init__.py
crdata/datasets/INTERACTION/config.yaml
crdata/datasets/INTERACTION/factory.py
crdata/datasets/INTERACTION/implementation.py
crdata/datasets/INTERACTION/maps/BGR_Intersection-1.xml
crdata/datasets/INTERACTION/maps/CHN_Merging-1.xml
crdata/datasets/INTERACTION/maps/CHN_Roundabout-1.xml
crdata/datasets/INTERACTION/maps/DEU_Merging-1.xml
crdata/datasets/INTERACTION/maps/DEU_Roundabout-1.xml
crdata/datasets/INTERACTION/maps/USA_Intersection-1.xml
crdata/datasets/INTERACTION/maps/USA_Intersection-2.xml
crdata/datasets/INTERACTION/maps/USA_Intersection-3.xml
crdata/datasets/INTERACTION/maps/USA_Intersection-4.xml
crdata/datasets/INTERACTION/maps/USA_Roundabout-1.xml
crdata/datasets/INTERACTION/maps/USA_Roundabout-2.xml
crdata/datasets/INTERACTION/maps/USA_Roundabout-3.xml
crdata/datasets/__init__.py
crdata/datasets/common/__init__.py
crdata/datasets/common/levelx_datasets.py
crdata/datasets/common/obstacle_utils.py
crdata/datasets/exiD/__init__.py
crdata/datasets/exiD/config.yaml
crdata/datasets/exiD/factory.py
crdata/datasets/exiD/maps/DEU_AachenBrand-1.xml
crdata/datasets/exiD/maps/DEU_AachenLaurensberg-1.xml
crdata/datasets/exiD/maps/DEU_BergheimRoemer-1.xml
crdata/datasets/exiD/maps/DEU_CologneButzweiler-1.xml
commonroad_dataset_converter-2025.1.0.dist-info/LICENSE
commonroad_dataset_converter-2025.1.0.dist-info/METADATA
commonroad_dataset_converter-2025.1.0.dist-info/WHEEL
commonroad_dataset_converter-2025.1.0.dist-info/entry_points.txt
commonroad_dataset_converter-2025.1.0.dist-info/RECORD
