Metadata-Version: 2.3
Name: commonroad-dataset-converter
Version: 2025.1.0
Summary: CommonRoad Dataset Converter
License: BSD-3-Clause
Author: Cyber-Physical Systems Group, Technical University of Munich
Author-email: commonroad@lists.lrz.de
Requires-Python: >=3.10,<3.12
Classifier: License :: OSI Approved :: BSD License
Classifier: Operating System :: OS Independent
Classifier: Programming Language :: Python
Classifier: Programming Language :: Python :: 3
Classifier: Programming Language :: Python :: 3.10
Classifier: Programming Language :: Python :: 3.11
Classifier: Programming Language :: Python :: 3.9
Requires-Dist: click (<=8.1)
Requires-Dist: commonroad-clcs (>=2025.2.0,<2026.0.0)
Requires-Dist: commonroad-drivability-checker (>=2025.3.1,<2026.0.0)
Requires-Dist: commonroad-io (>=2024.2,<2025.0)
Requires-Dist: commonroad-route-planner (>=2025.1.0,<2026.0.0)
Requires-Dist: numpy (>=1.21,<2.0)
Requires-Dist: pandas (>=0.24.2)
Requires-Dist: pyarrow (>=10.0.1)
Requires-Dist: pydantic (>=2.3.0,<3.0.0)
Requires-Dist: pyproj (>=3.4.0,<4.0.0)
Requires-Dist: ruamel-yaml (>=0.16.10)
Requires-Dist: scipy (>=1.4.1)
Requires-Dist: tqdm (>=4.64.1,<5.0.0)
Requires-Dist: typer (>=0.9,<0.13)
Project-URL: Homepage, https://commonroad.in.tum.de
